MANIFEST.in
README.rst
pyproject.toml
run_tests.py
sandbox.py
setup.cfg
setup.py
algopy/__init__.py
algopy/_npversion.py
algopy/_six.py
algopy/base_type.py
algopy/compound.py
algopy/exact_interpolation.py
algopy/globalfuncs.py
algopy/utils.py
algopy/version.py
algopy.egg-info/PKG-INFO
algopy.egg-info/SOURCES.txt
algopy.egg-info/dependency_links.txt
algopy.egg-info/requires.txt
algopy.egg-info/top_level.txt
algopy/fft/__init__.py
algopy/fft/fft.py
algopy/linalg/__init__.py
algopy/linalg/compound.py
algopy/linalg/linalg.py
algopy/nthderiv/__init__.py
algopy/nthderiv/nthderiv.py
algopy/special/__init__.py
algopy/special/compound.py
algopy/special/special.py
algopy/tests/__init__.py
algopy/tests/test_compound.py
algopy/tests/test_exact_interpolation.py
algopy/tests/test_examples.py
algopy/tests/test_globalfuncs.py
algopy/tests/test_linalg.py
algopy/tests/test_npversion.py
algopy/tests/test_nthderiv.py
algopy/tests/test_operators.py
algopy/tests/test_special.py
algopy/tests/test_utils.py
algopy/tracer/__init__.py
algopy/tracer/tracer.py
algopy/tracer/tests/__init__.py
algopy/tracer/tests/environment.py
algopy/tracer/tests/test_future_division.py
algopy/tracer/tests/test_tracer.py
algopy/tracer/tests/test_tracer_complex.py
algopy/tracer/tests/test_output/__init__.py
algopy/utpm/__init__.py
algopy/utpm/algorithms.py
algopy/utpm/utpm.py
algopy/utpm/tests/__init__.py
algopy/utpm/tests/test_algorithms.py
algopy/utpm/tests/test_special_function_identities.py
algopy/utpm/tests/test_utpm.py
algopy/utpm/tests/test_utpm_complex.py
algopy/utpm/tests/test_utpm_convenience.py
documentation/getting_started.py
documentation/AD_tutorial_TU_Berlin/example1_qr.py
documentation/AD_tutorial_TU_Berlin/example2_qr_numerical_stability.py
documentation/AD_tutorial_TU_Berlin/example3_qr_for_moore_penrose_pseudo_inverse.py
documentation/AD_tutorial_TU_Berlin/example4_eigh.py
documentation/AD_tutorial_TU_Berlin/example5_code_tracing_with_pyadolc.py
documentation/AD_tutorial_TU_Berlin/example6_utps_simple_function.py
documentation/AD_tutorial_TU_Berlin/example7_simple_computation_of_the_hessian.py
