Metadata-Version: 2.1
Name: algopy
Version: 0.7.2
Summary: ALGOPY: Taylor Arithmetic Computation and Algorithmic Differentiation
Home-page: https://packages.python.org/algopy
Author: Sebastian F. Walter
Author-email: Sebastian Walter <sebastian.walter@gmail.com>, Alexander Griffing <argriffi@ncsu.edu>
Maintainer-email: "Sebastian F. Walter" <sebastian.walter@gmail.com>
License: BSD
Project-URL: Homepage, https://www.github.com/b45ch1/algopy
Project-URL: Documentation, https://pythonhosted.org/algopy/
Project-URL: Repository, https://www.github.com/b45ch1/algopy
Project-URL: Changelog, https://github.com/b45ch1/algopy/blob/master/CHANGELOG.rst
Keywords: algorithmic differentiation,computational differentiation,automatic differentiation,forward mode,reverse mode,Taylor arithmetic
Platform: all
Requires-Python: >=3.6
Requires-Dist: numpy>=2.0.0
Requires-Dist: scipy>=1.14.0
Requires-Dist: pytest>=8.2.2
